setup.py
smilectl/__init__.py
smilectl/api.py
smilectl/utils.py
smilectl.egg-info/PKG-INFO
smilectl.egg-info/SOURCES.txt
smilectl.egg-info/dependency_links.txt
smilectl.egg-info/entry_points.txt
smilectl.egg-info/not-zip-safe
smilectl.egg-info/requires.txt
smilectl.egg-info/top_level.txt
smilectl/lib/job.libsm