Metadata-Version: 1.0
Name: smilectl
Version: 0.0.3
Summary: Smile Lab job launch tool.
Home-page: https://zhengxu.work/
Author: UNKNOWN
Author-email: UNKNOWN
License: UNKNOWN
Platform: UNKNOWN
